fdtools/__init__.py
fdtools/dirtools/__init__.py
fdtools/dirtools/core.py
fdtools/filetools/__init__.py
fdtools/filetools/core.py
fdtools-0.0.1.0.dist-info/LICENSE
fdtools-0.0.1.0.dist-info/METADATA
fdtools-0.0.1.0.dist-info/WHEEL
fdtools-0.0.1.0.dist-info/top_level.txt
fdtools-0.0.1.0.dist-info/RECORD
